<Defs>
  <ThoughtDef>
    <defName>mostlytraits_SkillOpinionOffset</defName>
     <thoughtClass>Thought_SituationalSocial</thoughtClass>
    <workerClass>mostlytraits.ThoughtWorker_Skill</workerClass>
    <validWhileDespawned>true</validWhileDespawned>
    <nullifyingTraits>
      <li>weird_neutral05</li>
    </nullifyingTraits>
<developmentalStageFilter>Baby, Child, Adult</developmentalStageFilter>
    <stages>
      <li>
        <label>respectable doctor</label>
        <baseOpinionOffset>10</baseOpinionOffset>
      </li>
    </stages>
  </ThoughtDef>
</Defs>